[
    {
        "time": "2025-12-18T00:00:00Z",
        "values": {
            "altimeterSetting": 1019.26,
            "cloudBase": 2.9,
            "cloudCeiling": 2.9,
            "cloudCover": 100,
            "dewPoint": 4.3,
            "evapotranspiration": 0.07,
            "freezingRainIntensity": 0,
            "humidity": 67,
            "iceAccumulation": 0,
            "iceAccumulationLwe": 0,
            "precipitationProbability": 0,
            "pressureSeaLevel": 1020.12,
            "pressureSurfaceLevel": 978.66,
            "rainAccumulation": 0,
            "rainIntensity": 0,
            "sleetAccumulation": 0,
            "sleetAccumulationLwe": 0,
            "sleetIntensity": 0,
            "snowAccumulation": 0,
            "snowAccumulationLwe": 0,
            "snowDepth": null,
            "snowIntensity": 0,
            "temperature": 10.1,
            "temperatureApparent": 10.1,
            "uvHealthConcern": 0,
            "uvIndex": 0,
            "visibility": 16,
            "weatherCode": 1001,
            "windDirection": 145,
            "windGust": 3.3,
            "windSpeed": 1.3
        }
    },
    {
        "time": "2025-12-18T01:00:00Z",
        "values": {
            "altimeterSetting": 1017.93,
            "cloudBase": 3.1,
            "cloudCeiling": null,
            "cloudCover": 40,
            "dewPoint": 1.8,
            "evapotranspiration": 0.064,
            "freezingRainIntensity": 0,
            "humidity": 59,
            "iceAccumulation": 0,
            "iceAccumulationLwe": 0,
            "precipitationProbability": 0,
            "pressureSeaLevel": 1017.64,
            "pressureSurfaceLevel": 978.35,
            "rainAccumulation": 0,
            "rainIntensity": 0,
            "sleetAccumulation": 0,
            "sleetAccumulationLwe": 0,
            "sleetIntensity": 0,
            "snowAccumulation": 0,
            "snowAccumulationLwe": 0,
            "snowDepth": null,
            "snowIntensity": 0,
            "temperature": 8.6,
            "temperatureApparent": 8.6,
            "uvHealthConcern": 0,
            "uvIndex": 0,
            "visibility": 16,
            "weatherCode": 1101,
            "windDirection": 151,
            "windGust": 4.8,
            "windSpeed": 3
        }
    },
    {
        "time": "2025-12-18T02:00:00Z",
        "values": {
            "altimeterSetting": 1018.68,
            "cloudBase": 2.9,
            "cloudCeiling": 3.1,
            "cloudCover": 100,
            "dewPoint": -0.5,
            "evapotranspiration": 0.064,
            "freezingRainIntensity": 0,
            "humidity": 50,
            "iceAccumulation": 0,
            "iceAccumulationLwe": 0,
            "precipitationProbability": 19,
            "pressureSeaLevel": 1018.4,
            "pressureSurfaceLevel": 979.08,
            "rainAccumulation": 0.11,
            "rainIntensity": 0.39,
            "sleetAccumulation": 0,
            "sleetAccumulationLwe": 0,
            "sleetIntensity": 0,
            "snowAccumulation": 0,
            "snowAccumulationLwe": 0,
            "snowDepth": null,
            "snowIntensity": 0,
            "temperature": 8.7,
            "temperatureApparent": 8.7,
            "uvHealthConcern": 0,
            "uvIndex": 0,
            "visibility": 16,
            "weatherCode": 4000,
            "windDirection": 145,
            "windGust": 5,
            "windSpeed": 2.6
        }
    },
    {
        "time": "2025-12-18T03:00:00Z",
        "values": {
            "altimeterSetting": 1018.34,
            "cloudBase": 3.3,
            "cloudCeiling": 3.1,
            "cloudCover": 100,
            "dewPoint": -2.6,
            "evapotranspiration": 0.067,
            "freezingRainIntensity": 0,
            "humidity": 42,
            "iceAccumulation": 0,
            "iceAccumulationLwe": 0,
            "precipitationProbability": 0,
            "pressureSeaLevel": 1018.09,
            "pressureSurfaceLevel": 978.75,
            "rainAccumulation": 0.09,
            "rainIntensity": 0,
            "sleetAccumulation": 0,
            "sleetAccumulationLwe": 0,
            "sleetIntensity": 0,
            "snowAccumulation": 0,
            "snowAccumulationLwe": 0,
            "snowDepth": null,
            "snowIntensity": 0,
            "temperature": 9.1,
            "temperatureApparent": 9.1,
            "uvHealthConcern": 0,
            "uvIndex": 0,
            "visibility": 16,
            "weatherCode": 1001,
            "windDirection": 161,
            "windGust": 6,
            "windSpeed": 3.2
        }
    },
    {
        "time": "2025-12-18T04:00:00Z",
        "values": {
            "altimeterSetting": 1017.55,
            "cloudBase": 3.3,
            "cloudCeiling": 3.1,
            "cloudCover": 100,
            "dewPoint": -3.8,
            "evapotranspiration": 0.069,
            "freezingRainIntensity": 0,
            "humidity": 38,
            "iceAccumulation": 0,
            "iceAccumulationLwe": 0,
            "precipitationProbability": 0,
            "pressureSeaLevel": 1017.19,
            "pressureSurfaceLevel": 977.98,
            "rainAccumulation": 0,
            "rainIntensity": 0,
            "sleetAccumulation": 0,
            "sleetAccumulationLwe": 0,
            "sleetIntensity": 0,
            "snowAccumulation": 0,
            "snowAccumulationLwe": 0,
            "snowDepth": null,
            "snowIntensity": 0,
            "temperature": 9,
            "temperatureApparent": 9,
            "uvHealthConcern": 0,
            "uvIndex": 0,
            "visibility": 16,
            "weatherCode": 1001,
            "windDirection": 167,
            "windGust": 7.3,
            "windSpeed": 3.8
        }
    },
    {
        "time": "2025-12-18T05:00:00Z",
        "values": {
            "altimeterSetting": 1016.61,
            "cloudBase": 3.3,
            "cloudCeiling": null,
            "cloudCover": 61,
            "dewPoint": -4.3,
            "evapotranspiration": 0.072,
            "freezingRainIntensity": 0,
            "humidity": 36,
            "iceAccumulation": 0,
            "iceAccumulationLwe": 0,
            "precipitationProbability": 0,
            "pressureSeaLevel": 1016.37,
            "pressureSurfaceLevel": 977.07,
            "rainAccumulation": 0,
            "rainIntensity": 0,
            "sleetIntensity": 0,
            "snowAccumulation": 0,
            "snowAccumulationLwe": 0,
            "snowDepth": null,
            "snowIntensity": 0,
            "temperature": 9,
            "temperatureApparent": 9,
            "uvHealthConcern": 0,
            "uvIndex": 0,
            "visibility": 16,
            "weatherCode": 1101,
            "windDirection": 159,
            "windGust": 7.4,
            "windSpeed": 4.2
        }
    },
    {
        "time": "2025-12-18T06:00:00Z",
        "values": {
            "altimeterSetting": 1016.07,
            "cloudBase": null,
            "cloudCeiling": null,
            "cloudCover": 9,
            "dewPoint": -2.8,
            "evapotranspiration": 0.065,
            "freezingRainIntensity": 0,
            "humidity": 42,
            "iceAccumulation": 0,
            "iceAccumulationLwe": 0,
            "precipitationProbability": 0,
            "pressureSeaLevel": 1015.75,
            "pressureSurfaceLevel": 976.55,
            "rainAccumulation": 0,
            "rainIntensity": 0,
            "sleetIntensity": 0,
            "snowAccumulation": 0,
            "snowAccumulationLwe": 0,
            "snowDepth": null,
            "snowIntensity": 0,
            "temperature": 8.2,
            "temperatureApparent": 8.2,
            "uvHealthConcern": 0,
            "uvIndex": 0,
            "visibility": 16,
            "weatherCode": 1000,
            "windDirection": 161,
            "windGust": 8.1,
            "windSpeed": 4.5
        }
    },
    {
        "time": "2025-12-18T07:00:00Z",
        "values": {
            "altimeterSetting": 1016.02,
            "cloudBase": 2.9,
            "cloudCeiling": 2.7,
            "cloudCover": 100,
            "dewPoint": -1.8,
            "evapotranspiration": 0.063,
            "freezingRainIntensity": 0,
            "humidity": 44,
            "iceAccumulation": 0,
            "iceAccumulationLwe": 0,
            "precipitationProbability": 0,
            "pressureSeaLevel": 1015.7,
            "pressureSurfaceLevel": 976.51,
            "rainAccumulation": 0,
            "rainIntensity": 0,
            "sleetIntensity": 0,
            "snowAccumulation": 0,
            "snowAccumulationLwe": 0,
            "snowDepth": null,
            "snowIntensity": 0,
            "temperature": 9.1,
            "temperatureApparent": 9.1,
            "uvHealthConcern": 0,
            "uvIndex": 0,
            "visibility": 16,
            "weatherCode": 1001,
            "windDirection": 163,
            "windGust": 8.4,
            "windSpeed": 4.9
        }
    },
    {
        "time": "2025-12-18T08:00:00Z",
        "values": {
            "altimeterSetting": 1015.66,
            "cloudBase": 2.9,
            "cloudCeiling": 2.9,
            "cloudCover": 100,
            "dewPoint": 0.8,
            "evapotranspiration": 0.057,
            "freezingRainIntensity": 0,
            "humidity": 51,
            "iceAccumulation": 0,
            "iceAccumulationLwe": 0,
            "precipitationProbability": 0,
            "pressureSeaLevel": 1015.33,
            "pressureSurfaceLevel": 976.15,
            "rainAccumulation": 0,
            "rainIntensity": 0,
            "sleetIntensity": 0,
            "snowAccumulation": 0,
            "snowAccumulationLwe": 0,
            "snowDepth": null,
            "snowIntensity": 0,
            "temperature": 9.4,
            "temperatureApparent": 9.4,
            "uvHealthConcern": 0,
            "uvIndex": 0,
            "visibility": 16,
            "weatherCode": 1001,
            "windDirection": 163,
            "windGust": 9.9,
            "windSpeed": 6.2
        }
    },
    {
        "time": "2025-12-18T09:00:00Z",
        "values": {
            "altimeterSetting": 1015.13,
            "cloudBase": null,
            "cloudCeiling": null,
            "cloudCover": 25,
            "dewPoint": 3.2,
            "evapotranspiration": 0.047,
            "freezingRainIntensity": 0,
            "humidity": 62,
            "iceAccumulation": 0,
            "iceAccumulationLwe": 0,
            "precipitationProbability": 0,
            "pressureSeaLevel": 1014.82,
            "pressureSurfaceLevel": 975.64,
            "rainAccumulation": 0,
            "rainIntensity": 0,
            "sleetIntensity": 0,
            "snowAccumulation": 0,
            "snowAccumulationLwe": 0,
            "snowDepth": null,
            "snowIntensity": 0,
            "temperature": 9,
            "temperatureApparent": 9,
            "uvHealthConcern": 0,
            "uvIndex": 0,
            "visibility": 16,
            "weatherCode": 1100,
            "windDirection": 164,
            "windGust": 10.6,
            "windSpeed": 6.6
        }
    },
    {
        "time": "2025-12-18T10:00:00Z",
        "values": {
            "altimeterSetting": 1014.72,
            "cloudBase": null,
            "cloudCeiling": null,
            "cloudCover": 6,
            "dewPoint": 4.8,
            "evapotranspiration": 0.044,
            "freezingRainIntensity": 0,
            "humidity": 71,
            "iceAccumulation": 0,
            "iceAccumulationLwe": 0,
            "precipitationProbability": 0,
            "pressureSeaLevel": 1014.38,
            "pressureSurfaceLevel": 975.24,
            "rainAccumulation": 0,
            "rainIntensity": 0,
            "sleetIntensity": 0,
            "snowAccumulation": 0,
            "snowAccumulationLwe": 0,
            "snowDepth": null,
            "snowIntensity": 0,
            "temperature": 8.7,
            "temperatureApparent": 8.7,
            "uvHealthConcern": 0,
            "uvIndex": 0,
            "visibility": 16,
            "weatherCode": 1000,
            "windDirection": 163,
            "windGust": 10.4,
            "windSpeed": 6.3
        }
    },
    {
        "time": "2025-12-18T11:00:00Z",
        "values": {
            "altimeterSetting": 1014.52,
            "cloudBase": null,
            "cloudCeiling": null,
            "cloudCover": 0,
            "dewPoint": 6.1,
            "evapotranspiration": 0.035,
            "freezingRainIntensity": 0,
            "humidity": 78,
            "iceAccumulation": 0,
            "iceAccumulationLwe": 0,
            "precipitationProbability": 0,
            "pressureSeaLevel": 1014.09,
            "pressureSurfaceLevel": 975.05,
            "rainAccumulation": 0,
            "rainIntensity": 0,
            "sleetIntensity": 0,
            "snowAccumulation": 0,
            "snowAccumulationLwe": 0,
            "snowDepth": null,
            "snowIntensity": 0,
            "temperature": 8.7,
            "temperatureApparent": 8.7,
            "uvHealthConcern": 0,
            "uvIndex": 0,
            "visibility": 16,
            "weatherCode": 1000,
            "windDirection": 163,
            "windGust": 10.3,
            "windSpeed": 6.3
        }
    },
    {
        "time": "2025-12-18T12:00:00Z",
        "values": {
            "altimeterSetting": 1013.8,
            "cloudBase": 4.5,
            "cloudCeiling": 8.8,
            "cloudCover": 97,
            "dewPoint": 7.4,
            "evapotranspiration": 0.027,
            "freezingRainIntensity": 0,
            "humidity": 83,
            "iceAccumulation": 0,
            "iceAccumulationLwe": 0,
            "precipitationProbability": 0,
            "pressureSeaLevel": 1013.34,
            "pressureSurfaceLevel": 974.35,
            "rainAccumulation": 0,
            "rainIntensity": 0,
            "sleetIntensity": 0,
            "snowAccumulation": 0,
            "snowAccumulationLwe": 0,
            "snowDepth": null,
            "snowIntensity": 0,
            "temperature": 9.1,
            "temperatureApparent": 9.1,
            "uvHealthConcern": 0,
            "uvIndex": 0,
            "visibility": 16,
            "weatherCode": 1001,
            "windDirection": 161,
            "windGust": 10,
            "windSpeed": 5.9
        }
    },
    {
        "time": "2025-12-18T13:00:00Z",
        "values": {
            "altimeterSetting": 1013.69,
            "cloudBase": 4.7,
            "cloudCeiling": 7.7,
            "cloudCover": 100,
            "dewPoint": 8.3,
            "evapotranspiration": 0.027,
            "freezingRainIntensity": 0,
            "humidity": 85,
            "iceAccumulation": 0,
            "iceAccumulationLwe": 0,
            "precipitationProbability": 0,
            "pressureSeaLevel": 1013.23,
            "pressureSurfaceLevel": 974.25,
            "rainAccumulation": 0,
            "rainIntensity": 0,
            "sleetIntensity": 0,
            "snowAccumulation": 0,
            "snowAccumulationLwe": 0,
            "snowDepth": null,
            "snowIntensity": 0,
            "temperature": 9.8,
            "temperatureApparent": 9.8,
            "uvHealthConcern": 0,
            "uvIndex": 0,
            "visibility": 15.74,
            "weatherCode": 1001,
            "windDirection": 166,
            "windGust": 10.2,
            "windSpeed": 6.4
        }
    },
    {
        "time": "2025-12-18T14:00:00Z",
        "values": {
            "altimeterSetting": 1013.97,
            "cloudBase": 2,
            "cloudCeiling": null,
            "cloudCover": 100,
            "dewPoint": 8.4,
            "evapotranspiration": 0.039,
            "freezingRainIntensity": 0,
            "humidity": 84,
            "iceAccumulation": 0,
            "iceAccumulationLwe": 0,
            "precipitationProbability": 0,
            "pressureSeaLevel": 1013.72,
            "pressureSurfaceLevel": 974.52,
            "rainAccumulation": 0,
            "rainIntensity": 0,
            "sleetIntensity": 0,
            "snowAccumulation": 0,
            "snowAccumulationLwe": 0,
            "snowDepth": null,
            "snowIntensity": 0,
            "temperature": 10.4,
            "temperatureApparent": 10.4,
            "uvHealthConcern": 0,
            "uvIndex": 0,
            "visibility": 16,
            "weatherCode": 1001,
            "windDirection": 165,
            "windGust": 13.2,
            "windSpeed": 7.4
        }
    },
    {
        "time": "2025-12-18T15:00:00Z",
        "values": {
            "altimeterSetting": 1013.29,
            "cloudBase": 2.1,
            "cloudCeiling": null,
            "cloudCover": 100,
            "dewPoint": 9.5,
            "evapotranspiration": 0.042,
            "freezingRainIntensity": 0,
            "humidity": 88,
            "iceAccumulation": 0,
            "iceAccumulationLwe": 0,
            "precipitationProbability": 30,
            "pressureSeaLevel": 1013.05,
            "pressureSurfaceLevel": 973.86,
            "rainAccumulation": 0.5,
            "rainIntensity": 1.61,
            "sleetIntensity": 0,
            "snowAccumulation": 0,
            "snowAccumulationLwe": 0,
            "snowDepth": null,
            "snowIntensity": 0,
            "temperature": 11,
            "temperatureApparent": 11,
            "uvHealthConcern": 0,
            "uvIndex": 0,
            "visibility": 5.97,
            "weatherCode": 4200,
            "windDirection": 168,
            "windGust": 14.2,
            "windSpeed": 6.5
        }
    },
    {
        "time": "2025-12-18T16:00:00Z",
        "values": {
            "altimeterSetting": 1011.87,
            "cloudBase": 1.9,
            "cloudCeiling": 1.9,
            "cloudCover": 100,
            "dewPoint": 11,
            "evapotranspiration": 0.01,
            "freezingRainIntensity": 0,
            "humidity": 89,
            "iceAccumulation": 0,
            "iceAccumulationLwe": 0,
            "precipitationProbability": 60,
            "pressureSeaLevel": 1011.78,
            "pressureSurfaceLevel": 972.66,
            "rainAccumulation": 1.01,
            "rainIntensity": 1.52,
            "sleetIntensity": 0,
            "snowAccumulation": 0,
            "snowAccumulationLwe": 0,
            "snowDepth": null,
            "snowIntensity": 0,
            "temperature": 12.7,
            "temperatureApparent": 12.7,
            "uvHealthConcern": 0,
            "uvIndex": 1,
            "visibility": 6.58,
            "weatherCode": 4200,
            "windDirection": 174,
            "windGust": 15.9,
            "windSpeed": 7.4
        }
    },
    {
        "time": "2025-12-18T17:00:00Z",
        "values": {
            "altimeterSetting": 1012.04,
            "cloudBase": 2.1,
            "cloudCeiling": 0.8,
            "cloudCover": 100,
            "dewPoint": 10.9,
            "evapotranspiration": 0.01,
            "freezingRainIntensity": 0,
            "humidity": 85,
            "iceAccumulation": 0,
            "iceAccumulationLwe": 0,
            "precipitationProbability": 0,
            "pressureSeaLevel": 1011.84,
            "pressureSurfaceLevel": 972.65,
            "rainAccumulation": 0,
            "rainIntensity": 0,
            "sleetIntensity": 0,
            "snowAccumulation": 0,
            "snowAccumulationLwe": 0,
            "snowDepth": null,
            "snowIntensity": 0,
            "temperature": 13.2,
            "temperatureApparent": 13.2,
            "uvHealthConcern": 0,
            "uvIndex": 1,
            "visibility": 16,
            "weatherCode": 1001,
            "windDirection": 173,
            "windGust": 17.9,
            "windSpeed": 8.5
        }
    },
    {
        "time": "2025-12-18T18:00:00Z",
        "values": {
            "altimeterSetting": 1009.84,
            "cloudBase": 2.4,
            "cloudCeiling": null,
            "cloudCover": 96,
            "dewPoint": 11.3,
            "evapotranspiration": 0.013,
            "freezingRainIntensity": 0,
            "humidity": 86,
            "iceAccumulation": 0,
            "iceAccumulationLwe": 0,
            "precipitationProbability": 0,
            "pressureSeaLevel": 1009.68,
            "pressureSurfaceLevel": 970.52,
            "rainAccumulation": 0.28,
            "rainIntensity": 0,
            "sleetIntensity": 0,
            "snowAccumulation": 0,
            "snowAccumulationLwe": 0,
            "snowDepth": null,
            "snowIntensity": 0,
            "temperature": 13.5,
            "temperatureApparent": 13.5,
            "uvHealthConcern": 0,
            "uvIndex": 0,
            "visibility": 15.7,
            "weatherCode": 1001,
            "windDirection": 166,
            "windGust": 18.7,
            "windSpeed": 9
        }
    },
    {
        "time": "2025-12-18T19:00:00Z",
        "values": {
            "altimeterSetting": 1009.14,
            "cloudBase": 2.4,
            "cloudCeiling": 2.3,
            "cloudCover": 100,
            "dewPoint": 11.2,
            "evapotranspiration": 0.011,
            "freezingRainIntensity": 0,
            "humidity": 83,
            "iceAccumulation": 0,
            "iceAccumulationLwe": 0,
            "precipitationProbability": 40,
            "pressureSeaLevel": 1008.92,
            "pressureSurfaceLevel": 969.84,
            "rainAccumulation": 0,
            "rainIntensity": 0.44,
            "sleetIntensity": 0,
            "snowAccumulation": 0,
            "snowAccumulationLwe": 0,
            "snowDepth": null,
            "snowIntensity": 0,
            "temperature": 13.9,
            "temperatureApparent": 13.9,
            "uvHealthConcern": 0,
            "uvIndex": 0,
            "visibility": 14.29,
            "weatherCode": 4000,
            "windDirection": 173,
            "windGust": 17.4,
            "windSpeed": 8.9
        }
    },
    {
        "time": "2025-12-18T20:00:00Z",
        "values": {
            "altimeterSetting": 1008.42,
            "cloudBase": 1.8,
            "cloudCeiling": 1.8,
            "cloudCover": 100,
            "dewPoint": 10.7,
            "evapotranspiration": 0.017,
            "freezingRainIntensity": 0,
            "humidity": 83,
            "iceAccumulation": 0,
            "iceAccumulationLwe": 0,
            "precipitationProbability": 0,
            "pressureSeaLevel": 1008.05,
            "pressureSurfaceLevel": 969.14,
            "rainAccumulation": 0,
            "rainIntensity": 0,
            "sleetIntensity": 0,
            "snowAccumulation": 0,
            "snowAccumulationLwe": 0,
            "snowDepth": null,
            "snowIntensity": 0,
            "temperature": 12.6,
            "temperatureApparent": 12.6,
            "uvHealthConcern": 0,
            "uvIndex": 0,
            "visibility": 16,
            "weatherCode": 1001,
            "windDirection": 167,
            "windGust": 14.4,
            "windSpeed": 7.4
        }
    },
    {
        "time": "2025-12-18T21:00:00Z",
        "values": {
            "altimeterSetting": 1007.72,
            "cloudBase": 1.3,
            "cloudCeiling": 2.3,
            "cloudCover": 100,
            "dewPoint": 10.6,
            "evapotranspiration": 0.034,
            "freezingRainIntensity": 0,
            "humidity": 87,
            "iceAccumulation": 0,
            "iceAccumulationLwe": 0,
            "precipitationProbability": 45,
            "pressureSeaLevel": 1007.28,
            "pressureSurfaceLevel": 968.47,
            "rainAccumulation": 1.61,
            "rainIntensity": 0.53,
            "sleetIntensity": 0,
            "snowAccumulation": 0,
            "snowAccumulationLwe": 0,
            "snowDepth": null,
            "snowIntensity": 0,
            "temperature": 12,
            "temperatureApparent": 12,
            "uvHealthConcern": 0,
            "uvIndex": 0,
            "visibility": 13.82,
            "weatherCode": 4200,
            "windDirection": 173,
            "windGust": 15.7,
            "windSpeed": 8.2
        }
    },
    {
        "time": "2025-12-18T22:00:00Z",
        "values": {
            "altimeterSetting": 1006.76,
            "cloudBase": 1,
            "cloudCeiling": 2.6,
            "cloudCover": 100,
            "dewPoint": 11.3,
            "evapotranspiration": 0.039,
            "freezingRainIntensity": 0,
            "humidity": 91,
            "iceAccumulation": 0,
            "iceAccumulationLwe": 0,
            "precipitationProbability": 60,
            "pressureSeaLevel": 1006.36,
            "pressureSurfaceLevel": 967.54,
            "rainAccumulation": 2.07,
            "rainIntensity": 2.59,
            "sleetIntensity": 0,
            "snowAccumulation": 0,
            "snowAccumulationLwe": 0,
            "snowDepth": null,
            "snowIntensity": 0,
            "temperature": 12.1,
            "temperatureApparent": 12.1,
            "uvHealthConcern": 0,
            "uvIndex": 0,
            "visibility": 5.41,
            "weatherCode": 4001,
            "windDirection": 179,
            "windGust": 18.4,
            "windSpeed": 8.9
        }
    },
    {
        "time": "2025-12-18T23:00:00Z",
        "values": {
            "altimeterSetting": 1006.25,
            "cloudBase": 0.6,
            "cloudCeiling": 0.6,
            "cloudCover": 100,
            "dewPoint": 11.8,
            "evapotranspiration": 0.035,
            "freezingRainIntensity": 0,
            "humidity": 93,
            "iceAccumulation": 0,
            "iceAccumulationLwe": 0,
            "precipitationProbability": 0,
            "pressureSeaLevel": 1005.82,
            "pressureSurfaceLevel": 967.04,
            "rainAccumulation": 1.68,
            "rainIntensity": 0,
            "sleetIntensity": 0,
            "snowAccumulation": 0,
            "snowAccumulationLwe": 0,
            "snowDepth": null,
            "snowIntensity": 0,
            "temperature": 12.3,
            "temperatureApparent": 12.3,
            "uvHealthConcern": 0,
            "uvIndex": 0,
            "visibility": 12.89,
            "weatherCode": 1001,
            "windDirection": 186,
            "windGust": 17.5,
            "windSpeed": 9.5
        }
    }
]